tests/__init__.py
tests/whooshstore_test.py
whooshstore/__init__.py
whooshstore/util.py
whooshstore/version.py
whooshstore-0.1.data/scripts/ws
whooshstore-0.1.data/scripts/ws-update
whooshstore-0.1.dist-info/DESCRIPTION.rst
whooshstore-0.1.dist-info/METADATA
whooshstore-0.1.dist-info/RECORD
whooshstore-0.1.dist-info/WHEEL
whooshstore-0.1.dist-info/metadata.json
whooshstore-0.1.dist-info/top_level.txt
